openai_functools/__init__.py
openai_functools/function_spec.py
openai_functools/functions_orchestrator.py
openai_functools/metadata_generator.py
openai_functools/openai_types.py
openai_functools/utils/__init__.py
openai_functools/utils/conversation.py
openai_functools-1.1.131.dist-info/LICENSE
openai_functools-1.1.131.dist-info/METADATA
openai_functools-1.1.131.dist-info/WHEEL
openai_functools-1.1.131.dist-info/RECORD
