Metadata-Version: 2.1
Name: openai_functools
Version: 1.1.131
Summary: python openai functions tooling
Author: Jakob Serlier
Author-email: 37184788+Jakob-98@users.noreply.github.com
Requires-Python: >=3.8.1,<4.0.0
Classifier: Programming Language :: Python :: 3
Classifier: Programming Language :: Python :: 3.9
Classifier: Programming Language :: Python :: 3.10
Classifier: Programming Language :: Python :: 3.11
Classifier: Programming Language :: Python :: 3.12
Requires-Dist: black (>=23.7.0,<24.0.0)
Requires-Dist: docstring-parser (>=0.15,<0.16)
Requires-Dist: flake8 (>=6.0.0,<7.0.0)
Requires-Dist: isort (>=5.12.0,<6.0.0)
Requires-Dist: openai (>=1.7.2,<2.0.0)
Requires-Dist: pytest (>=7.4.0,<8.0.0)
